xvcl/__init__.py
xvcl/compiler.py
xvcl/py.typed
xvcl-2.5.0.dist-info/METADATA
xvcl-2.5.0.dist-info/WHEEL
xvcl-2.5.0.dist-info/entry_points.txt
xvcl-2.5.0.dist-info/licenses/LICENSE
xvcl-2.5.0.dist-info/RECORD
