Metadata-Version: 2.4
Name: xvcl
Version: 2.5.0
Summary: Extended VCL compiler with metaprogramming features for Fastly VCL
Author-email: Frank Denis <github@pureftpd.org>
License: MIT
License-File: LICENSE
Keywords: compiler,fastly,preprocessor,varnish,vcl
Classifier: Development Status :: 4 - Beta
Classifier: Intended Audience :: Developers
Classifier: License :: OSI Approved :: MIT License
Classifier: Programming Language :: Python :: 3
Classifier: Programming Language :: Python :: 3.9
Classifier: Programming Language :: Python :: 3.10
Classifier: Programming Language :: Python :: 3.11
Classifier: Programming Language :: Python :: 3.12
Classifier: Topic :: Software Development :: Compilers
Requires-Python: >=3.9
Provides-Extra: dev
Requires-Dist: mypy>=1.0.0; extra == 'dev'
Requires-Dist: pytest>=7.0.0; extra == 'dev'
Requires-Dist: ruff>=0.1.0; extra == 'dev'
